idealkr_django_core/__init__.py
idealkr_django_core/mixins.py
idealkr_django_core-0.1.dist-info/METADATA
idealkr_django_core-0.1.dist-info/WHEEL
idealkr_django_core-0.1.dist-info/top_level.txt
idealkr_django_core-0.1.dist-info/RECORD
